dbca_utils-2.1.4.dist-info/METADATA
dbca_utils-2.1.4.dist-info/WHEEL
dbca_utils-2.1.4.dist-info/entry_points.txt
dbca_utils-2.1.4.dist-info/licenses/LICENSE
dbca_utils/__init__.py
dbca_utils/middleware.py
dbca_utils/models.py
dbca_utils/utils.py
dbca_utils-2.1.4.dist-info/RECORD
