Metadata-Version: 2.4
Name: dbca-utils
Version: 2.1.4
Summary: Utilities for DBCA Django apps
Author-Email: Rocky Chen <rocky.chen@dbca.wa.gov.au>, Ashley Felton <ashley.felton@dbca.wa.gov.au>
License-Expression: Apache-2.0
Classifier: Framework :: Django
Classifier: Framework :: Django :: 4.2
Classifier: Framework :: Django :: 5.0
Classifier: Framework :: Django :: 5.2
Classifier: Environment :: Web Environment
Classifier: Intended Audience :: Developers
Classifier: Development Status :: 5 - Production/Stable
Classifier: Programming Language :: Python
Classifier: Programming Language :: Python :: 3
Classifier: Programming Language :: Python :: 3.10
Classifier: Programming Language :: Python :: 3.11
Classifier: Programming Language :: Python :: 3.12
Classifier: Programming Language :: Python :: 3.13
Classifier: Topic :: Software Development :: Libraries
Classifier: Topic :: Software Development :: Libraries :: Python Modules
Project-URL: Homepage, https://github.com/dbca-wa/dbca-utils
Project-URL: Repository, https://github.com/dbca-wa/dbca-utils.git
Project-URL: Changelog, https://github.com/dbca-wa/dbca-utils/blob/master/CHANGELOG.md
Project-URL: GitHub, https://github.com/dbca-wa/dbca-utils
Requires-Python: <4.0,>=3.10
Requires-Dist: django<6,>=4.2
Requires-Dist: markupsafe==3.0.3
